{"data":{"headline":"Crossword No 431634","type":"games","meta":{"pdf":"crossword-20161009-19333.pdf","print_index":"print.html"},"copy":{"title":"Crossword No 431634","id":"19333","description":"","publisher":"The Sun","setter":"","byline":"","date-publish":"Sunday, 09 October 2016","date-publish-email":"09 October 2016","date-publish-analytics":"2016/10/09 00:00 sunday","date-release":"2016-10-09 00:00:00","date-solution":"2016-10-10 00:00:00","crosswordtype":"Two Speed","correctsolutionmessagetext":"You've done it!","previoussolutiontext":"Previous crossword solution","previoussolutionlink":"http://feeds.thesun.co.uk/puzzles/crossword/20161008/19332/","type":"block","gridsize":{"type":null,"cols":"13","rows":"13"},"settings":{"solution_hashed":"2178b18157f8814a65fd733b603a00e6","solution":"STAIRCASE NIPP I E M A E RENROL AUSTEREE P I Z T D VDROPSHOT ISLE  R H N O   NEITHER SPROUTX   D F E R  CURB LEARNINGE E E R E G ERECOVER TEASEP A E I T M STIP NECTARINE"},"hints":{"Mark Errors":"0","Solve Letter":"0","Solve Word":"0","Ask A Friend":"0"},"clues":[{"name":"Description","title":"Across","clues":[{"word":1,"number":"1","clue":"Flight that sometimes continues after landing","format":"9","length":9,"answer":"STAIRCASE"},{"word":2,"number":"6","clue":"Pinch cut, though not at first","format":"3","length":3,"answer":"NIP"},{"word":3,"number":"8","clue":"Sign up when rolling inside","format":"5","length":5,"answer":"ENROL"},{"word":4,"number":"9","clue":"Stern authoress, unfinished, half-read","format":"7","length":7,"answer":"AUSTERE"},{"word":5,"number":"10","clue":"Lets go fiery tennis stroke","format":"4,4","length":8,"answer":"DROPSHOT"},{"word":6,"number":"11","clue":"Misleading part of small landmass","format":"4","length":4,"answer":"ISLE"},{"word":7,"number":"13","clue":"Whichever of two or three I organised","format":"6","length":6,"answer":"EITHER"},{"word":8,"number":"14","clue":"Spring up and run into jet","format":"6","length":6,"answer":"SPROUT"},{"word":9,"number":"17","clue":"Stop, we're told by side of the road","format":"4","length":4,"answer":"CURB"},{"word":10,"number":"19","clue":"Fifty getting wage, picking things up","format":"8","length":8,"answer":"LEARNING"},{"word":11,"number":"22","clue":"Get better work as an upholsterer","format":"7","length":7,"answer":"RECOVER"},{"word":12,"number":"23","clue":"Time to relax, then torment","format":"5","length":5,"answer":"TEASE"},{"word":13,"number":"24","clue":"Clue list","format":"3","length":3,"answer":"TIP"},{"word":14,"number":"25","clue":"Delicious drink in England, initially, with fruit","format":"9","length":9,"answer":"NECTARINE"}]},{"name":"Description","title":"Down","clues":[{"word":15,"number":"1","clue":"Swiftness of ranked player holding Penny","format":"5","length":5,"answer":"SPEED"},{"word":16,"number":"2","clue":"Dry wine at Heathrow, for example","format":"7","length":7,"answer":"AIRPORT"},{"word":17,"number":"3","clue":"Very much enjoyed playing with her slide","format":"8","length":8,"answer":"RELISHED"},{"word":18,"number":"4","clue":"Warlike woman finds South American river","format":"6","length":6,"answer":"AMAZON"},{"word":19,"number":"5","clue":"Partly turn the radio set's aerial in this direction","format":"4","length":4,"answer":"EAST"},{"word":20,"number":"6","clue":"Wants massages, we hear","format":"5","length":5,"answer":"NEEDS"},{"word":21,"number":"7","clue":"Stop before opening","format":"7","length":7,"answer":"PREVENT"},{"word":22,"number":"12","clue":"Latte reportedly holds back musical offering","format":"8","length":8,"answer":"OPERETTA"},{"word":23,"number":"13","clue":"Passage, but around beginning of road","format":"7","length":7,"answer":"EXCERPT"},{"word":24,"number":"15","clue":"Circle city motorway with clever paper-folding!","format":"7","length":7,"answer":"ORIGAMI"},{"word":25,"number":"16","clue":"Some prefer rickshaws made of iron","format":"6","length":6,"answer":"FERRIC"},{"word":26,"number":"18","clue":"Summarise on the subject of hat","format":"5","length":5,"answer":"RECAP"},{"word":27,"number":"20","clue":"For example about to view returning birds","format":"5","length":5,"answer":"GEESE"},{"word":28,"number":"21","clue":"Still prevented entry","format":"4","length":4,"answer":"EVEN"}]},{"name":"Description","title":"Across","clues":[{"word":1,"number":"1","clue":"Flight between floors","format":"9","length":9,"answer":"STAIRCASE"},{"word":2,"number":"6","clue":"Bite or pinch","format":"3","length":3,"answer":"NIP"},{"word":3,"number":"8","clue":"Join a course","format":"5","length":5,"answer":"ENROL"},{"word":4,"number":"9","clue":"Bare, harsh","format":"7","length":7,"answer":"AUSTERE"},{"word":5,"number":"10","clue":"Tennis return","format":"4,4","length":8,"answer":"DROPSHOT"},{"word":6,"number":"11","clue":"Man or Wight, eg","format":"4","length":4,"answer":"ISLE"},{"word":7,"number":"13","clue":"Any of two","format":"6","length":6,"answer":"EITHER"},{"word":8,"number":"14","clue":"Germinate","format":"6","length":6,"answer":"SPROUT"},{"word":9,"number":"17","clue":"Check","format":"4","length":4,"answer":"CURB"},{"word":10,"number":"19","clue":"Education","format":"8","length":8,"answer":"LEARNING"},{"word":11,"number":"22","clue":"Become healthy again","format":"7","length":7,"answer":"RECOVER"},{"word":12,"number":"23","clue":"Irritate playfully","format":"5","length":5,"answer":"TEASE"},{"word":13,"number":"24","clue":"Betting suggestion","format":"3","length":3,"answer":"TIP"},{"word":14,"number":"25","clue":"Peach-like fruit","format":"9","length":9,"answer":"NECTARINE"}]},{"name":"Description","title":"Down","clues":[{"word":15,"number":"1","clue":"Drive too fast","format":"5","length":5,"answer":"SPEED"},{"word":16,"number":"2","clue":"Aviation terminal","format":"7","length":7,"answer":"AIRPORT"},{"word":17,"number":"3","clue":"Enjoyed","format":"8","length":8,"answer":"RELISHED"},{"word":18,"number":"4","clue":"Brazilian river","format":"6","length":6,"answer":"AMAZON"},{"word":19,"number":"5","clue":"Cardinal point","format":"4","length":4,"answer":"EAST"},{"word":20,"number":"6","clue":"Calls for","format":"5","length":5,"answer":"NEEDS"},{"word":21,"number":"7","clue":"Hinder","format":"7","length":7,"answer":"PREVENT"},{"word":22,"number":"12","clue":"Light musical drama","format":"8","length":8,"answer":"OPERETTA"},{"word":23,"number":"13","clue":"Film clip","format":"7","length":7,"answer":"EXCERPT"},{"word":24,"number":"15","clue":"Art of paper-folding","format":"7","length":7,"answer":"ORIGAMI"},{"word":25,"number":"16","clue":"Of iron","format":"6","length":6,"answer":"FERRIC"},{"word":26,"number":"18","clue":"Briefly summarise","format":"5","length":5,"answer":"RECAP"},{"word":27,"number":"20","clue":"Farmyard birds","format":"5","length":5,"answer":"GEESE"},{"word":28,"number":"21","clue":"All square","format":"4","length":4,"answer":"EVEN"}]}],"words":[{"id":1,"x":"1-9","y":"1","solution":"STAIRCASE"},{"id":2,"x":"11-13","y":"1","solution":"NIP"},{"id":3,"x":"1-5","y":"3","solution":"ENROL"},{"id":4,"x":"7-13","y":"3","solution":"AUSTERE"},{"id":5,"x":"1-8","y":"5","solution":"DROPSHOT"},{"id":6,"x":"10-13","y":"5","solution":"ISLE"},{"id":7,"x":"1-6","y":"7","solution":"EITHER"},{"id":8,"x":"8-13","y":"7","solution":"SPROUT"},{"id":9,"x":"1-4","y":"9","solution":"CURB"},{"id":10,"x":"6-13","y":"9","solution":"LEARNING"},{"id":11,"x":"1-7","y":"11","solution":"RECOVER"},{"id":12,"x":"9-13","y":"11","solution":"TEASE"},{"id":13,"x":"1-3","y":"13","solution":"TIP"},{"id":14,"x":"5-13","y":"13","solution":"NECTARINE"},{"id":15,"x":"1","y":"1-5","solution":"SPEED"},{"id":16,"x":"3","y":"1-7","solution":"AIRPORT"},{"id":17,"x":"5","y":"1-8","solution":"RELISHED"},{"id":18,"x":"7","y":"1-6","solution":"AMAZON"},{"id":19,"x":"9","y":"1-4","solution":"EAST"},{"id":20,"x":"11","y":"1-5","solution":"NEEDS"},{"id":21,"x":"13","y":"1-7","solution":"PREVENT"},{"id":22,"x":"9","y":"6-13","solution":"OPERETTA"},{"id":23,"x":"1","y":"7-13","solution":"EXCERPT"},{"id":24,"x":"11","y":"7-13","solution":"ORIGAMI"},{"id":25,"x":"7","y":"8-13","solution":"FERRIC"},{"id":26,"x":"3","y":"9-13","solution":"RECAP"},{"id":27,"x":"13","y":"9-13","solution":"GEESE"},{"id":28,"x":"5","y":"10-13","solution":"EVEN"}]},"competitioncrossword":"0","grid":[[{"SquareID":1,"Number":"1","Letter":"S","Blank":"","WordAcrossID":"1","WordDownID":"15"},{"SquareID":2,"Number":"","Letter":"T","Blank":"","WordAcrossID":"1","WordDownID":""},{"SquareID":3,"Number":"2","Letter":"A","Blank":"","WordAcrossID":"1","WordDownID":"16"},{"SquareID":4,"Number":"","Letter":"I","Blank":"","WordAcrossID":"1","WordDownID":""},{"SquareID":5,"Number":"3","Letter":"R","Blank":"","WordAcrossID":"1","WordDownID":"17"},{"SquareID":6,"Number":"","Letter":"C","Blank":"","WordAcrossID":"1","WordDownID":""},{"SquareID":7,"Number":"4","Letter":"A","Blank":"","WordAcrossID":"1","WordDownID":"18"},{"SquareID":8,"Number":"","Letter":"S","Blank":"","WordAcrossID":"1","WordDownID":""},{"SquareID":9,"Number":"5","Letter":"E","Blank":"","WordAcrossID":"1","WordDownID":"19"},{"SquareID":10,"Number":"","Letter":"","Blank":"blank","WordAcrossID":"","WordDownID":""},{"SquareID":11,"Number":"6","Letter":"N","Blank":"","WordAcrossID":"2","WordDownID":"20"},{"SquareID":12,"Number":"","Letter":"I","Blank":"","WordAcrossID":"2","WordDownID":""},{"SquareID":13,"Number":"7","Letter":"P","Blank":"","WordAcrossID":"2","WordDownID":"21"}],[{"SquareID":14,"Number":"","Letter":"P","Blank":"","WordAcrossID":"","WordDownID":"15"},{"SquareID":15,"Number":"","Letter":"","Blank":"blank","WordAcrossID":"","WordDownID":""},{"SquareID":16,"Number":"","Letter":"I","Blank":"","WordAcrossID":"","WordDownID":"16"},{"SquareID":17,"Number":"","Letter":"","Blank":"blank","WordAcrossID":"","WordDownID":""},{"SquareID":18,"Number":"","Letter":"E","Blank":"","WordAcrossID":"","WordDownID":"17"},{"SquareID":19,"Number":"","Letter":"","Blank":"blank","WordAcrossID":"","WordDownID":""},{"SquareID":20,"Number":"","Letter":"M","Blank":"","WordAcrossID":"","WordDownID":"18"},{"SquareID":21,"Number":"","Letter":"","Blank":"blank","WordAcrossID":"","WordDownID":""},{"SquareID":22,"Number":"","Letter":"A","Blank":"","WordAcrossID":"","WordDownID":"19"},{"SquareID":23,"Number":"","Letter":"","Blank":"blank","WordAcrossID":"","WordDownID":""},{"SquareID":24,"Number":"","Letter":"E","Blank":"","WordAcrossID":"","WordDownID":"20"},{"SquareID":25,"Number":"","Letter":"","Blank":"blank","WordAcrossID":"","WordDownID":""},{"SquareID":26,"Number":"","Letter":"R","Blank":"","WordAcrossID":"","WordDownID":"21"}],[{"SquareID":27,"Number":"8","Letter":"E","Blank":"","WordAcrossID":"3","WordDownID":"15"},{"SquareID":28,"Number":"","Letter":"N","Blank":"","WordAcrossID":"3","WordDownID":""},{"SquareID":29,"Number":"","Letter":"R","Blank":"","WordAcrossID":"3","WordDownID":"16"},{"SquareID":30,"Number":"","Letter":"O","Blank":"","WordAcrossID":"3","WordDownID":""},{"SquareID":31,"Number":"","Letter":"L","Blank":"","WordAcrossID":"3","WordDownID":"17"},{"SquareID":32,"Number":"","Letter":"","Blank":"blank","WordAcrossID":"","WordDownID":""},{"SquareID":33,"Number":"9","Letter":"A","Blank":"","WordAcrossID":"4","WordDownID":"18"},{"SquareID":34,"Number":"","Letter":"U","Blank":"","WordAcrossID":"4","WordDownID":""},{"SquareID":35,"Number":"","Letter":"S","Blank":"","WordAcrossID":"4","WordDownID":"19"},{"SquareID":36,"Number":"","Letter":"T","Blank":"","WordAcrossID":"4","WordDownID":""},{"SquareID":37,"Number":"","Letter":"E","Blank":"","WordAcrossID":"4","WordDownID":"20"},{"SquareID":38,"Number":"","Letter":"R","Blank":"","WordAcrossID":"4","WordDownID":""},{"SquareID":39,"Number":"","Letter":"E","Blank":"","WordAcrossID":"4","WordDownID":"21"}],[{"SquareID":40,"Number":"","Letter":"E","Blank":"","WordAcrossID":"","WordDownID":"15"},{"SquareID":41,"Number":"","Letter":"","Blank":"blank","WordAcrossID":"","WordDownID":""},{"SquareID":42,"Number":"","Letter":"P","Blank":"","WordAcrossID":"","WordDownID":"16"},{"SquareID":43,"Number":"","Letter":"","Blank":"blank","WordAcrossID":"","WordDownID":""},{"SquareID":44,"Number":"","Letter":"I","Blank":"","WordAcrossID":"","WordDownID":"17"},{"SquareID":45,"Number":"","Letter":"","Blank":"blank","WordAcrossID":"","WordDownID":""},{"SquareID":46,"Number":"","Letter":"Z","Blank":"","WordAcrossID":"","WordDownID":"18"},{"SquareID":47,"Number":"","Letter":"","Blank":"blank","WordAcrossID":"","WordDownID":""},{"SquareID":48,"Number":"","Letter":"T","Blank":"","WordAcrossID":"","WordDownID":"19"},{"SquareID":49,"Number":"","Letter":"","Blank":"blank","WordAcrossID":"","WordDownID":""},{"SquareID":50,"Number":"","Letter":"D","Blank":"","WordAcrossID":"","WordDownID":"20"},{"SquareID":51,"Number":"","Letter":"","Blank":"blank","WordAcrossID":"","WordDownID":""},{"SquareID":52,"Number":"","Letter":"V","Blank":"","WordAcrossID":"","WordDownID":"21"}],[{"SquareID":53,"Number":"10","Letter":"D","Blank":"","WordAcrossID":"5","WordDownID":"15"},{"SquareID":54,"Number":"","Letter":"R","Blank":"","WordAcrossID":"5","WordDownID":""},{"SquareID":55,"Number":"","Letter":"O","Blank":"","WordAcrossID":"5","WordDownID":"16"},{"SquareID":56,"Number":"","Letter":"P","Blank":"","WordAcrossID":"5","WordDownID":""},{"SquareID":57,"Number":"","Letter":"S","Blank":"","WordAcrossID":"5","WordDownID":"17"},{"SquareID":58,"Number":"","Letter":"H","Blank":"","WordAcrossID":"5","WordDownID":""},{"SquareID":59,"Number":"","Letter":"O","Blank":"","WordAcrossID":"5","WordDownID":"18"},{"SquareID":60,"Number":"","Letter":"T","Blank":"","WordAcrossID":"5","WordDownID":""},{"SquareID":61,"Number":"","Letter":"","Blank":"blank","WordAcrossID":"","WordDownID":""},{"SquareID":62,"Number":"11","Letter":"I","Blank":"","WordAcrossID":"6","WordDownID":""},{"SquareID":63,"Number":"","Letter":"S","Blank":"","WordAcrossID":"6","WordDownID":"20"},{"SquareID":64,"Number":"","Letter":"L","Blank":"","WordAcrossID":"6","WordDownID":""},{"SquareID":65,"Number":"","Letter":"E","Blank":"","WordAcrossID":"6","WordDownID":"21"}],[{"SquareID":66,"Number":"","Letter":"","Blank":"blank","WordAcrossID":"","WordDownID":""},{"SquareID":67,"Number":"","Letter":"","Blank":"blank","WordAcrossID":"","WordDownID":""},{"SquareID":68,"Number":"","Letter":"R","Blank":"","WordAcrossID":"","WordDownID":"16"},{"SquareID":69,"Number":"","Letter":"","Blank":"blank","WordAcrossID":"","WordDownID":""},{"SquareID":70,"Number":"","Letter":"H","Blank":"","WordAcrossID":"","WordDownID":"17"},{"SquareID":71,"Number":"","Letter":"","Blank":"blank","WordAcrossID":"","WordDownID":""},{"SquareID":72,"Number":"","Letter":"N","Blank":"","WordAcrossID":"","WordDownID":"18"},{"SquareID":73,"Number":"","Letter":"","Blank":"blank","WordAcrossID":"","WordDownID":""},{"SquareID":74,"Number":"12","Letter":"O","Blank":"","WordAcrossID":"","WordDownID":"22"},{"SquareID":75,"Number":"","Letter":"","Blank":"blank","WordAcrossID":"","WordDownID":""},{"SquareID":76,"Number":"","Letter":"","Blank":"blank","WordAcrossID":"","WordDownID":""},{"SquareID":77,"Number":"","Letter":"","Blank":"blank","WordAcrossID":"","WordDownID":""},{"SquareID":78,"Number":"","Letter":"N","Blank":"","WordAcrossID":"","WordDownID":"21"}],[{"SquareID":79,"Number":"13","Letter":"E","Blank":"","WordAcrossID":"7","WordDownID":"23"},{"SquareID":80,"Number":"","Letter":"I","Blank":"","WordAcrossID":"7","WordDownID":""},{"SquareID":81,"Number":"","Letter":"T","Blank":"","WordAcrossID":"7","WordDownID":"16"},{"SquareID":82,"Number":"","Letter":"H","Blank":"","WordAcrossID":"7","WordDownID":""},{"SquareID":83,"Number":"","Letter":"E","Blank":"","WordAcrossID":"7","WordDownID":"17"},{"SquareID":84,"Number":"","Letter":"R","Blank":"","WordAcrossID":"7","WordDownID":""},{"SquareID":85,"Number":"","Letter":"","Blank":"blank","WordAcrossID":"","WordDownID":""},{"SquareID":86,"Number":"14","Letter":"S","Blank":"","WordAcrossID":"8","WordDownID":""},{"SquareID":87,"Number":"","Letter":"P","Blank":"","WordAcrossID":"8","WordDownID":"22"},{"SquareID":88,"Number":"","Letter":"R","Blank":"","WordAcrossID":"8","WordDownID":""},{"SquareID":89,"Number":"15","Letter":"O","Blank":"","WordAcrossID":"8","WordDownID":"24"},{"SquareID":90,"Number":"","Letter":"U","Blank":"","WordAcrossID":"8","WordDownID":""},{"SquareID":91,"Number":"","Letter":"T","Blank":"","WordAcrossID":"8","WordDownID":"21"}],[{"SquareID":92,"Number":"","Letter":"X","Blank":"","WordAcrossID":"","WordDownID":"23"},{"SquareID":93,"Number":"","Letter":"","Blank":"blank","WordAcrossID":"","WordDownID":""},{"SquareID":94,"Number":"","Letter":"","Blank":"blank","WordAcrossID":"","WordDownID":""},{"SquareID":95,"Number":"","Letter":"","Blank":"blank","WordAcrossID":"","WordDownID":""},{"SquareID":96,"Number":"","Letter":"D","Blank":"","WordAcrossID":"","WordDownID":"17"},{"SquareID":97,"Number":"","Letter":"","Blank":"blank","WordAcrossID":"","WordDownID":""},{"SquareID":98,"Number":"16","Letter":"F","Blank":"","WordAcrossID":"","WordDownID":"25"},{"SquareID":99,"Number":"","Letter":"","Blank":"blank","WordAcrossID":"","WordDownID":""},{"SquareID":100,"Number":"","Letter":"E","Blank":"","WordAcrossID":"","WordDownID":"22"},{"SquareID":101,"Number":"","Letter":"","Blank":"blank","WordAcrossID":"","WordDownID":""},{"SquareID":102,"Number":"","Letter":"R","Blank":"","WordAcrossID":"","WordDownID":"24"},{"SquareID":103,"Number":"","Letter":"","Blank":"blank","WordAcrossID":"","WordDownID":""},{"SquareID":104,"Number":"","Letter":"","Blank":"blank","WordAcrossID":"","WordDownID":""}],[{"SquareID":105,"Number":"17","Letter":"C","Blank":"","WordAcrossID":"9","WordDownID":"23"},{"SquareID":106,"Number":"","Letter":"U","Blank":"","WordAcrossID":"9","WordDownID":""},{"SquareID":107,"Number":"18","Letter":"R","Blank":"","WordAcrossID":"9","WordDownID":"26"},{"SquareID":108,"Number":"","Letter":"B","Blank":"","WordAcrossID":"9","WordDownID":""},{"SquareID":109,"Number":"","Letter":"","Blank":"blank","WordAcrossID":"","WordDownID":""},{"SquareID":110,"Number":"19","Letter":"L","Blank":"","WordAcrossID":"10","WordDownID":""},{"SquareID":111,"Number":"","Letter":"E","Blank":"","WordAcrossID":"10","WordDownID":"25"},{"SquareID":112,"Number":"","Letter":"A","Blank":"","WordAcrossID":"10","WordDownID":""},{"SquareID":113,"Number":"","Letter":"R","Blank":"","WordAcrossID":"10","WordDownID":"22"},{"SquareID":114,"Number":"","Letter":"N","Blank":"","WordAcrossID":"10","WordDownID":""},{"SquareID":115,"Number":"","Letter":"I","Blank":"","WordAcrossID":"10","WordDownID":"24"},{"SquareID":116,"Number":"","Letter":"N","Blank":"","WordAcrossID":"10","WordDownID":""},{"SquareID":117,"Number":"20","Letter":"G","Blank":"","WordAcrossID":"10","WordDownID":"27"}],[{"SquareID":118,"Number":"","Letter":"E","Blank":"","WordAcrossID":"","WordDownID":"23"},{"SquareID":119,"Number":"","Letter":"","Blank":"blank","WordAcrossID":"","WordDownID":""},{"SquareID":120,"Number":"","Letter":"E","Blank":"","WordAcrossID":"","WordDownID":"26"},{"SquareID":121,"Number":"","Letter":"","Blank":"blank","WordAcrossID":"","WordDownID":""},{"SquareID":122,"Number":"21","Letter":"E","Blank":"","WordAcrossID":"","WordDownID":"28"},{"SquareID":123,"Number":"","Letter":"","Blank":"blank","WordAcrossID":"","WordDownID":""},{"SquareID":124,"Number":"","Letter":"R","Blank":"","WordAcrossID":"","WordDownID":"25"},{"SquareID":125,"Number":"","Letter":"","Blank":"blank","WordAcrossID":"","WordDownID":""},{"SquareID":126,"Number":"","Letter":"E","Blank":"","WordAcrossID":"","WordDownID":"22"},{"SquareID":127,"Number":"","Letter":"","Blank":"blank","WordAcrossID":"","WordDownID":""},{"SquareID":128,"Number":"","Letter":"G","Blank":"","WordAcrossID":"","WordDownID":"24"},{"SquareID":129,"Number":"","Letter":"","Blank":"blank","WordAcrossID":"","WordDownID":""},{"SquareID":130,"Number":"","Letter":"E","Blank":"","WordAcrossID":"","WordDownID":"27"}],[{"SquareID":131,"Number":"22","Letter":"R","Blank":"","WordAcrossID":"11","WordDownID":"23"},{"SquareID":132,"Number":"","Letter":"E","Blank":"","WordAcrossID":"11","WordDownID":""},{"SquareID":133,"Number":"","Letter":"C","Blank":"","WordAcrossID":"11","WordDownID":"26"},{"SquareID":134,"Number":"","Letter":"O","Blank":"","WordAcrossID":"11","WordDownID":""},{"SquareID":135,"Number":"","Letter":"V","Blank":"","WordAcrossID":"11","WordDownID":"28"},{"SquareID":136,"Number":"","Letter":"E","Blank":"","WordAcrossID":"11","WordDownID":""},{"SquareID":137,"Number":"","Letter":"R","Blank":"","WordAcrossID":"11","WordDownID":"25"},{"SquareID":138,"Number":"","Letter":"","Blank":"blank","WordAcrossID":"","WordDownID":""},{"SquareID":139,"Number":"23","Letter":"T","Blank":"","WordAcrossID":"12","WordDownID":"22"},{"SquareID":140,"Number":"","Letter":"E","Blank":"","WordAcrossID":"12","WordDownID":""},{"SquareID":141,"Number":"","Letter":"A","Blank":"","WordAcrossID":"12","WordDownID":"24"},{"SquareID":142,"Number":"","Letter":"S","Blank":"","WordAcrossID":"12","WordDownID":""},{"SquareID":143,"Number":"","Letter":"E","Blank":"","WordAcrossID":"12","WordDownID":"27"}],[{"SquareID":144,"Number":"","Letter":"P","Blank":"","WordAcrossID":"","WordDownID":"23"},{"SquareID":145,"Number":"","Letter":"","Blank":"blank","WordAcrossID":"","WordDownID":""},{"SquareID":146,"Number":"","Letter":"A","Blank":"","WordAcrossID":"","WordDownID":"26"},{"SquareID":147,"Number":"","Letter":"","Blank":"blank","WordAcrossID":"","WordDownID":""},{"SquareID":148,"Number":"","Letter":"E","Blank":"","WordAcrossID":"","WordDownID":"28"},{"SquareID":149,"Number":"","Letter":"","Blank":"blank","WordAcrossID":"","WordDownID":""},{"SquareID":150,"Number":"","Letter":"I","Blank":"","WordAcrossID":"","WordDownID":"25"},{"SquareID":151,"Number":"","Letter":"","Blank":"blank","WordAcrossID":"","WordDownID":""},{"SquareID":152,"Number":"","Letter":"T","Blank":"","WordAcrossID":"","WordDownID":"22"},{"SquareID":153,"Number":"","Letter":"","Blank":"blank","WordAcrossID":"","WordDownID":""},{"SquareID":154,"Number":"","Letter":"M","Blank":"","WordAcrossID":"","WordDownID":"24"},{"SquareID":155,"Number":"","Letter":"","Blank":"blank","WordAcrossID":"","WordDownID":""},{"SquareID":156,"Number":"","Letter":"S","Blank":"","WordAcrossID":"","WordDownID":"27"}],[{"SquareID":157,"Number":"24","Letter":"T","Blank":"","WordAcrossID":"13","WordDownID":"23"},{"SquareID":158,"Number":"","Letter":"I","Blank":"","WordAcrossID":"13","WordDownID":""},{"SquareID":159,"Number":"","Letter":"P","Blank":"","WordAcrossID":"13","WordDownID":"26"},{"SquareID":160,"Number":"","Letter":"","Blank":"blank","WordAcrossID":"","WordDownID":""},{"SquareID":161,"Number":"25","Letter":"N","Blank":"","WordAcrossID":"14","WordDownID":"28"},{"SquareID":162,"Number":"","Letter":"E","Blank":"","WordAcrossID":"14","WordDownID":""},{"SquareID":163,"Number":"","Letter":"C","Blank":"","WordAcrossID":"14","WordDownID":"25"},{"SquareID":164,"Number":"","Letter":"T","Blank":"","WordAcrossID":"14","WordDownID":""},{"SquareID":165,"Number":"","Letter":"A","Blank":"","WordAcrossID":"14","WordDownID":"22"},{"SquareID":166,"Number":"","Letter":"R","Blank":"","WordAcrossID":"14","WordDownID":""},{"SquareID":167,"Number":"","Letter":"I","Blank":"","WordAcrossID":"14","WordDownID":"24"},{"SquareID":168,"Number":"","Letter":"N","Blank":"","WordAcrossID":"14","WordDownID":""},{"SquareID":169,"Number":"","Letter":"E","Blank":"","WordAcrossID":"14","WordDownID":"27"}]],"created":"2016-10-10 00:04:09"}}