{"clueProviders":[{"name":"Cryptic","acrossClues":[{"format":"5,6","text":"Weather warning device almost rings accidentally","number":"1","wordId":1},{"format":"3","text":"Ate drunken meal","number":"9","wordId":2},{"format":"7,2","text":"Stopping a picture before it's finished","number":"10","wordId":3},{"format":"8","text":"Cross, having to take back pictures and poetry","number":"11","wordId":4},{"format":"4","text":"Woodland deity colour, we're told","number":"12","wordId":5},{"format":"6","text":"In the team and entitled to score","number":"14","wordId":6},{"format":"6","text":"False praise for old country","number":"16","wordId":7},{"format":"4","text":"Copy baby's bed","number":"18","wordId":8},{"format":"8","text":"Some quadruped I greet, as thoroughbred","number":"19","wordId":9},{"format":"9","text":"Handle turned and guarded","number":"22","wordId":10},{"format":"3","text":"Black plane","number":"23","wordId":11},{"format":"7,4","text":"Forefront of knife?","number":"24","wordId":12}],"downClues":[{"format":"5","text":"Discovered in Tahiti, a radiant coronet","number":"2","wordId":13},{"format":"8","text":"Communist chiefs adored by Titian?","number":"3","wordId":14},{"format":"6","text":"Poles and English, thinly dispersed","number":"4","wordId":15},{"format":"4","text":"Profit from vitamin-enriched drink","number":"5","wordId":16},{"format":"7","text":"Sheepskin coats for dogs","number":"6","wordId":17},{"format":"11","text":"Instrument for picking up the beat?","number":"7","wordId":18},{"format":"11","text":"Impulsiveness at set point, any mistake?","number":"8","wordId":19},{"format":"8","text":"Excite again when modern reader is after right note","number":"13","wordId":20},{"format":"7","text":"Japanese therapy at sushi place","number":"15","wordId":21},{"format":"6","text":"Wizard flyer","number":"17","wordId":22},{"format":"5","text":"Change then dance again?","number":"20","wordId":23},{"format":"4","text":"Drink left","number":"21","wordId":24}]},{"name":"Coffee Time","acrossClues":[{"format":"5,6","text":"Hurricane warning","number":"1","wordId":1},{"format":"3","text":"Beverage","number":"9","wordId":2},{"format":"7,2","text":"Coming to a halt","number":"10","wordId":3},{"format":"8","text":"Cross","number":"11","wordId":4},{"format":"4","text":"Woodland deity","number":"12","wordId":5},{"format":"6","text":"Legal soccer position","number":"14","wordId":6},{"format":"6","text":"Former Iran","number":"16","wordId":7},{"format":"4","text":"Baby's bed","number":"18","wordId":8},{"format":"8","text":"Lineage","number":"19","wordId":9},{"format":"9","text":"Guarded","number":"22","wordId":10},{"format":"3","text":"Darkest black","number":"23","wordId":11},{"format":"7,4","text":"Avant-garde","number":"24","wordId":12}],"downClues":[{"format":"5","text":"Coronet","number":"2","wordId":13},{"format":"8","text":"Auburn-haired people","number":"3","wordId":14},{"format":"6","text":"Meagre","number":"4","wordId":15},{"format":"4","text":"Accrue","number":"5","wordId":16},{"format":"7","text":"Natives of Kabul's country","number":"6","wordId":17},{"format":"11","text":"Doctor's listening device","number":"7","wordId":18},{"format":"11","text":"Impulsiveness","number":"8","wordId":19},{"format":"8","text":"Light again","number":"13","wordId":20},{"format":"7","text":"Massage therapy","number":"15","wordId":21},{"format":"6","text":"Small falcon","number":"17","wordId":22},{"format":"5","text":"Amend, alter","number":"20","wordId":23},{"format":"4","text":"After-dinner drink","number":"21","wordId":24}]}],"id":"Sun29562","title":"Sun Crossword No 432053","datePublished":"2017-12-02T00:00:00","dateStarted":null,"duration":0,"solvingMode":0,"grid":[[{"guess":"","letter":"","number":"","selected":false,"wordSelected":false,"solvingMode":0,"autoSolved":false},{"guess":"","letter":"S","number":"1","selected":false,"wordSelected":false,"solvingMode":0,"autoSolved":false},{"guess":"","letter":"T","number":"2","selected":false,"wordSelected":false,"solvingMode":0,"autoSolved":false},{"guess":"","letter":"O","number":"","selected":false,"wordSelected":false,"solvingMode":0,"autoSolved":false},{"guess":"","letter":"R","number":"3","selected":false,"wordSelected":false,"solvingMode":0,"autoSolved":false},{"guess":"","letter":"M","number":"","selected":false,"wordSelected":false,"solvingMode":0,"autoSolved":false},{"guess":"","letter":"S","number":"4","selected":false,"wordSelected":false,"solvingMode":0,"autoSolved":false},{"guess":"","letter":"I","number":"","selected":false,"wordSelected":false,"solvingMode":0,"autoSolved":false},{"guess":"","letter":"G","number":"5","selected":false,"wordSelected":false,"solvingMode":0,"autoSolved":false},{"guess":"","letter":"N","number":"","selected":false,"wordSelected":false,"solvingMode":0,"autoSolved":false},{"guess":"","letter":"A","number":"6","selected":false,"wordSelected":false,"solvingMode":0,"autoSolved":false},{"guess":"","letter":"L","number":"","selected":false,"wordSelected":false,"solvingMode":0,"autoSolved":false},{"guess":"","letter":"","number":"","selected":false,"wordSelected":false,"solvingMode":0,"autoSolved":false}],[{"guess":"","letter":"S","number":"7","selected":false,"wordSelected":false,"solvingMode":0,"autoSolved":false},{"guess":"","letter":"","number":"","selected":false,"wordSelected":false,"solvingMode":0,"autoSolved":false},{"guess":"","letter":"I","number":"","selected":false,"wordSelected":false,"solvingMode":0,"autoSolved":false},{"guess":"","letter":"","number":"","selected":false,"wordSelected":false,"solvingMode":0,"autoSolved":false},{"guess":"","letter":"E","number":"","selected":false,"wordSelected":false,"solvingMode":0,"autoSolved":false},{"guess":"","letter":"","number":"","selected":false,"wordSelected":false,"solvingMode":0,"autoSolved":false},{"guess":"","letter":"P","number":"","selected":false,"wordSelected":false,"solvingMode":0,"autoSolved":false},{"guess":"","letter":"","number":"","selected":false,"wordSelected":false,"solvingMode":0,"autoSolved":false},{"guess":"","letter":"A","number":"","selected":false,"wordSelected":false,"solvingMode":0,"autoSolved":false},{"guess":"","letter":"","number":"","selected":false,"wordSelected":false,"solvingMode":0,"autoSolved":false},{"guess":"","letter":"F","number":"","selected":false,"wordSelected":false,"solvingMode":0,"autoSolved":false},{"guess":"","letter":"","number":"","selected":false,"wordSelected":false,"solvingMode":0,"autoSolved":false},{"guess":"","letter":"S","number":"8","selected":false,"wordSelected":false,"solvingMode":0,"autoSolved":false}],[{"guess":"","letter":"T","number":"9","selected":false,"wordSelected":false,"solvingMode":0,"autoSolved":false},{"guess":"","letter":"E","number":"","selected":false,"wordSelected":false,"solvingMode":0,"autoSolved":false},{"guess":"","letter":"A","number":"","selected":false,"wordSelected":false,"solvingMode":0,"autoSolved":false},{"guess":"","letter":"","number":"","selected":false,"wordSelected":false,"solvingMode":0,"autoSolved":false},{"guess":"","letter":"D","number":"10","selected":false,"wordSelected":false,"solvingMode":0,"autoSolved":false},{"guess":"","letter":"R","number":"","selected":false,"wordSelected":false,"solvingMode":0,"autoSolved":false},{"guess":"","letter":"A","number":"","selected":false,"wordSelected":false,"solvingMode":0,"autoSolved":false},{"guess":"","letter":"W","number":"","selected":false,"wordSelected":false,"solvingMode":0,"autoSolved":false},{"guess":"","letter":"I","number":"","selected":false,"wordSelected":false,"solvingMode":0,"autoSolved":false},{"guess":"","letter":"N","number":"","selected":false,"wordSelected":false,"solvingMode":0,"autoSolved":false},{"guess":"","letter":"G","number":"","selected":false,"wordSelected":false,"solvingMode":0,"autoSolved":false},{"guess":"","letter":"U","number":"","selected":false,"wordSelected":false,"solvingMode":0,"autoSolved":false},{"guess":"","letter":"P","number":"","selected":false,"wordSelected":false,"solvingMode":0,"autoSolved":false}],[{"guess":"","letter":"E","number":"","selected":false,"wordSelected":false,"solvingMode":0,"autoSolved":false},{"guess":"","letter":"","number":"","selected":false,"wordSelected":false,"solvingMode":0,"autoSolved":false},{"guess":"","letter":"R","number":"","selected":false,"wordSelected":false,"solvingMode":0,"autoSolved":false},{"guess":"","letter":"","number":"","selected":false,"wordSelected":false,"solvingMode":0,"autoSolved":false},{"guess":"","letter":"H","number":"","selected":false,"wordSelected":false,"solvingMode":0,"autoSolved":false},{"guess":"","letter":"","number":"","selected":false,"wordSelected":false,"solvingMode":0,"autoSolved":false},{"guess":"","letter":"R","number":"","selected":false,"wordSelected":false,"solvingMode":0,"autoSolved":false},{"guess":"","letter":"","number":"","selected":false,"wordSelected":false,"solvingMode":0,"autoSolved":false},{"guess":"","letter":"N","number":"","selected":false,"wordSelected":false,"solvingMode":0,"autoSolved":false},{"guess":"","letter":"","number":"","selected":false,"wordSelected":false,"solvingMode":0,"autoSolved":false},{"guess":"","letter":"H","number":"","selected":false,"wordSelected":false,"solvingMode":0,"autoSolved":false},{"guess":"","letter":"","number":"","selected":false,"wordSelected":false,"solvingMode":0,"autoSolved":false},{"guess":"","letter":"O","number":"","selected":false,"wordSelected":false,"solvingMode":0,"autoSolved":false}],[{"guess":"","letter":"T","number":"11","selected":false,"wordSelected":false,"solvingMode":0,"autoSolved":false},{"guess":"","letter":"R","number":"","selected":false,"wordSelected":false,"solvingMode":0,"autoSolved":false},{"guess":"","letter":"A","number":"","selected":false,"wordSelected":false,"solvingMode":0,"autoSolved":false},{"guess":"","letter":"V","number":"","selected":false,"wordSelected":false,"solvingMode":0,"autoSolved":false},{"guess":"","letter":"E","number":"","selected":false,"wordSelected":false,"solvingMode":0,"autoSolved":false},{"guess":"","letter":"R","number":"","selected":false,"wordSelected":false,"solvingMode":0,"autoSolved":false},{"guess":"","letter":"S","number":"","selected":false,"wordSelected":false,"solvingMode":0,"autoSolved":false},{"guess":"","letter":"E","number":"","selected":false,"wordSelected":false,"solvingMode":0,"autoSolved":false},{"guess":"","letter":"","number":"","selected":false,"wordSelected":false,"solvingMode":0,"autoSolved":false},{"guess":"","letter":"F","number":"12","selected":false,"wordSelected":false,"solvingMode":0,"autoSolved":false},{"guess":"","letter":"A","number":"","selected":false,"wordSelected":false,"solvingMode":0,"autoSolved":false},{"guess":"","letter":"U","number":"","selected":false,"wordSelected":false,"solvingMode":0,"autoSolved":false},{"guess":"","letter":"N","number":"","selected":false,"wordSelected":false,"solvingMode":0,"autoSolved":false}],[{"guess":"","letter":"H","number":"","selected":false,"wordSelected":false,"solvingMode":0,"autoSolved":false},{"guess":"","letter":"","number":"","selected":false,"wordSelected":false,"solvingMode":0,"autoSolved":false},{"guess":"","letter":"","number":"","selected":false,"wordSelected":false,"solvingMode":0,"autoSolved":false},{"guess":"","letter":"","number":"","selected":false,"wordSelected":false,"solvingMode":0,"autoSolved":false},{"guess":"","letter":"A","number":"","selected":false,"wordSelected":false,"solvingMode":0,"autoSolved":false},{"guess":"","letter":"","number":"","selected":false,"wordSelected":false,"solvingMode":0,"autoSolved":false},{"guess":"","letter":"E","number":"","selected":false,"wordSelected":false,"solvingMode":0,"autoSolved":false},{"guess":"","letter":"","number":"","selected":false,"wordSelected":false,"solvingMode":0,"autoSolved":false},{"guess":"","letter":"R","number":"13","selected":false,"wordSelected":false,"solvingMode":0,"autoSolved":false},{"guess":"","letter":"","number":"","selected":false,"wordSelected":false,"solvingMode":0,"autoSolved":false},{"guess":"","letter":"N","number":"","selected":false,"wordSelected":false,"solvingMode":0,"autoSolved":false},{"guess":"","letter":"","number":"","selected":false,"wordSelected":false,"solvingMode":0,"autoSolved":false},{"guess":"","letter":"T","number":"","selected":false,"wordSelected":false,"solvingMode":0,"autoSolved":false}],[{"guess":"","letter":"O","number":"14","selected":false,"wordSelected":false,"solvingMode":0,"autoSolved":false},{"guess":"","letter":"N","number":"","selected":false,"wordSelected":false,"solvingMode":0,"autoSolved":false},{"guess":"","letter":"S","number":"15","selected":false,"wordSelected":false,"solvingMode":0,"autoSolved":false},{"guess":"","letter":"I","number":"","selected":false,"wordSelected":false,"solvingMode":0,"autoSolved":false},{"guess":"","letter":"D","number":"","selected":false,"wordSelected":false,"solvingMode":0,"autoSolved":false},{"guess":"","letter":"E","number":"","selected":false,"wordSelected":false,"solvingMode":0,"autoSolved":false},{"guess":"","letter":"","number":"","selected":false,"wordSelected":false,"solvingMode":0,"autoSolved":false},{"guess":"","letter":"P","number":"16","selected":false,"wordSelected":false,"solvingMode":0,"autoSolved":false},{"guess":"","letter":"E","number":"","selected":false,"wordSelected":false,"solvingMode":0,"autoSolved":false},{"guess":"","letter":"R","number":"","selected":false,"wordSelected":false,"solvingMode":0,"autoSolved":false},{"guess":"","letter":"S","number":"","selected":false,"wordSelected":false,"solvingMode":0,"autoSolved":false},{"guess":"","letter":"I","number":"","selected":false,"wordSelected":false,"solvingMode":0,"autoSolved":false},{"guess":"","letter":"A","number":"","selected":false,"wordSelected":false,"solvingMode":0,"autoSolved":false}],[{"guess":"","letter":"S","number":"","selected":false,"wordSelected":false,"solvingMode":0,"autoSolved":false},{"guess":"","letter":"","number":"","selected":false,"wordSelected":false,"solvingMode":0,"autoSolved":false},{"guess":"","letter":"H","number":"","selected":false,"wordSelected":false,"solvingMode":0,"autoSolved":false},{"guess":"","letter":"","number":"","selected":false,"wordSelected":false,"solvingMode":0,"autoSolved":false},{"guess":"","letter":"S","number":"","selected":false,"wordSelected":false,"solvingMode":0,"autoSolved":false},{"guess":"","letter":"","number":"","selected":false,"wordSelected":false,"solvingMode":0,"autoSolved":false},{"guess":"","letter":"M","number":"17","selected":false,"wordSelected":false,"solvingMode":0,"autoSolved":false},{"guess":"","letter":"","number":"","selected":false,"wordSelected":false,"solvingMode":0,"autoSolved":false},{"guess":"","letter":"K","number":"","selected":false,"wordSelected":false,"solvingMode":0,"autoSolved":false},{"guess":"","letter":"","number":"","selected":false,"wordSelected":false,"solvingMode":0,"autoSolved":false},{"guess":"","letter":"","number":"","selected":false,"wordSelected":false,"solvingMode":0,"autoSolved":false},{"guess":"","letter":"","number":"","selected":false,"wordSelected":false,"solvingMode":0,"autoSolved":false},{"guess":"","letter":"N","number":"","selected":false,"wordSelected":false,"solvingMode":0,"autoSolved":false}],[{"guess":"","letter":"C","number":"18","selected":false,"wordSelected":false,"solvingMode":0,"autoSolved":false},{"guess":"","letter":"R","number":"","selected":false,"wordSelected":false,"solvingMode":0,"autoSolved":false},{"guess":"","letter":"I","number":"","selected":false,"wordSelected":false,"solvingMode":0,"autoSolved":false},{"guess":"","letter":"B","number":"","selected":false,"wordSelected":false,"solvingMode":0,"autoSolved":false},{"guess":"","letter":"","number":"","selected":false,"wordSelected":false,"solvingMode":0,"autoSolved":false},{"guess":"","letter":"P","number":"19","selected":false,"wordSelected":false,"solvingMode":0,"autoSolved":false},{"guess":"","letter":"E","number":"","selected":false,"wordSelected":false,"solvingMode":0,"autoSolved":false},{"guess":"","letter":"D","number":"","selected":false,"wordSelected":false,"solvingMode":0,"autoSolved":false},{"guess":"","letter":"I","number":"","selected":false,"wordSelected":false,"solvingMode":0,"autoSolved":false},{"guess":"","letter":"G","number":"","selected":false,"wordSelected":false,"solvingMode":0,"autoSolved":false},{"guess":"","letter":"R","number":"20","selected":false,"wordSelected":false,"solvingMode":0,"autoSolved":false},{"guess":"","letter":"E","number":"","selected":false,"wordSelected":false,"solvingMode":0,"autoSolved":false},{"guess":"","letter":"E","number":"","selected":false,"wordSelected":false,"solvingMode":0,"autoSolved":false}],[{"guess":"","letter":"O","number":"","selected":false,"wordSelected":false,"solvingMode":0,"autoSolved":false},{"guess":"","letter":"","number":"","selected":false,"wordSelected":false,"solvingMode":0,"autoSolved":false},{"guess":"","letter":"A","number":"","selected":false,"wordSelected":false,"solvingMode":0,"autoSolved":false},{"guess":"","letter":"","number":"","selected":false,"wordSelected":false,"solvingMode":0,"autoSolved":false},{"guess":"","letter":"P","number":"21","selected":false,"wordSelected":false,"solvingMode":0,"autoSolved":false},{"guess":"","letter":"","number":"","selected":false,"wordSelected":false,"solvingMode":0,"autoSolved":false},{"guess":"","letter":"R","number":"","selected":false,"wordSelected":false,"solvingMode":0,"autoSolved":false},{"guess":"","letter":"","number":"","selected":false,"wordSelected":false,"solvingMode":0,"autoSolved":false},{"guess":"","letter":"N","number":"","selected":false,"wordSelected":false,"solvingMode":0,"autoSolved":false},{"guess":"","letter":"","number":"","selected":false,"wordSelected":false,"solvingMode":0,"autoSolved":false},{"guess":"","letter":"E","number":"","selected":false,"wordSelected":false,"solvingMode":0,"autoSolved":false},{"guess":"","letter":"","number":"","selected":false,"wordSelected":false,"solvingMode":0,"autoSolved":false},{"guess":"","letter":"I","number":"","selected":false,"wordSelected":false,"solvingMode":0,"autoSolved":false}],[{"guess":"","letter":"P","number":"22","selected":false,"wordSelected":false,"solvingMode":0,"autoSolved":false},{"guess":"","letter":"A","number":"","selected":false,"wordSelected":false,"solvingMode":0,"autoSolved":false},{"guess":"","letter":"T","number":"","selected":false,"wordSelected":false,"solvingMode":0,"autoSolved":false},{"guess":"","letter":"R","number":"","selected":false,"wordSelected":false,"solvingMode":0,"autoSolved":false},{"guess":"","letter":"O","number":"","selected":false,"wordSelected":false,"solvingMode":0,"autoSolved":false},{"guess":"","letter":"L","number":"","selected":false,"wordSelected":false,"solvingMode":0,"autoSolved":false},{"guess":"","letter":"L","number":"","selected":false,"wordSelected":false,"solvingMode":0,"autoSolved":false},{"guess":"","letter":"E","number":"","selected":false,"wordSelected":false,"solvingMode":0,"autoSolved":false},{"guess":"","letter":"D","number":"","selected":false,"wordSelected":false,"solvingMode":0,"autoSolved":false},{"guess":"","letter":"","number":"","selected":false,"wordSelected":false,"solvingMode":0,"autoSolved":false},{"guess":"","letter":"J","number":"23","selected":false,"wordSelected":false,"solvingMode":0,"autoSolved":false},{"guess":"","letter":"E","number":"","selected":false,"wordSelected":false,"solvingMode":0,"autoSolved":false},{"guess":"","letter":"T","number":"","selected":false,"wordSelected":false,"solvingMode":0,"autoSolved":false}],[{"guess":"","letter":"E","number":"","selected":false,"wordSelected":false,"solvingMode":0,"autoSolved":false},{"guess":"","letter":"","number":"","selected":false,"wordSelected":false,"solvingMode":0,"autoSolved":false},{"guess":"","letter":"S","number":"","selected":false,"wordSelected":false,"solvingMode":0,"autoSolved":false},{"guess":"","letter":"","number":"","selected":false,"wordSelected":false,"solvingMode":0,"autoSolved":false},{"guess":"","letter":"R","number":"","selected":false,"wordSelected":false,"solvingMode":0,"autoSolved":false},{"guess":"","letter":"","number":"","selected":false,"wordSelected":false,"solvingMode":0,"autoSolved":false},{"guess":"","letter":"I","number":"","selected":false,"wordSelected":false,"solvingMode":0,"autoSolved":false},{"guess":"","letter":"","number":"","selected":false,"wordSelected":false,"solvingMode":0,"autoSolved":false},{"guess":"","letter":"L","number":"","selected":false,"wordSelected":false,"solvingMode":0,"autoSolved":false},{"guess":"","letter":"","number":"","selected":false,"wordSelected":false,"solvingMode":0,"autoSolved":false},{"guess":"","letter":"I","number":"","selected":false,"wordSelected":false,"solvingMode":0,"autoSolved":false},{"guess":"","letter":"","number":"","selected":false,"wordSelected":false,"solvingMode":0,"autoSolved":false},{"guess":"","letter":"Y","number":"","selected":false,"wordSelected":false,"solvingMode":0,"autoSolved":false}],[{"guess":"","letter":"","number":"","selected":false,"wordSelected":false,"solvingMode":0,"autoSolved":false},{"guess":"","letter":"C","number":"24","selected":false,"wordSelected":false,"solvingMode":0,"autoSolved":false},{"guess":"","letter":"U","number":"","selected":false,"wordSelected":false,"solvingMode":0,"autoSolved":false},{"guess":"","letter":"T","number":"","selected":false,"wordSelected":false,"solvingMode":0,"autoSolved":false},{"guess":"","letter":"T","number":"","selected":false,"wordSelected":false,"solvingMode":0,"autoSolved":false},{"guess":"","letter":"I","number":"","selected":false,"wordSelected":false,"solvingMode":0,"autoSolved":false},{"guess":"","letter":"N","number":"","selected":false,"wordSelected":false,"solvingMode":0,"autoSolved":false},{"guess":"","letter":"G","number":"","selected":false,"wordSelected":false,"solvingMode":0,"autoSolved":false},{"guess":"","letter":"E","number":"","selected":false,"wordSelected":false,"solvingMode":0,"autoSolved":false},{"guess":"","letter":"D","number":"","selected":false,"wordSelected":false,"solvingMode":0,"autoSolved":false},{"guess":"","letter":"G","number":"","selected":false,"wordSelected":false,"solvingMode":0,"autoSolved":false},{"guess":"","letter":"E","number":"","selected":false,"wordSelected":false,"solvingMode":0,"autoSolved":false},{"guess":"","letter":"","number":"","selected":false,"wordSelected":false,"solvingMode":0,"autoSolved":false}]],"words":[{"isAcross":true,"id":1,"x":2,"y":1,"length":11,"solvingMode":0,"selected":false},{"isAcross":true,"id":2,"x":1,"y":3,"length":3,"solvingMode":0,"selected":false},{"isAcross":true,"id":3,"x":5,"y":3,"length":9,"solvingMode":0,"selected":false},{"isAcross":true,"id":4,"x":1,"y":5,"length":8,"solvingMode":0,"selected":false},{"isAcross":true,"id":5,"x":10,"y":5,"length":4,"solvingMode":0,"selected":false},{"isAcross":true,"id":6,"x":1,"y":7,"length":6,"solvingMode":0,"selected":false},{"isAcross":true,"id":7,"x":8,"y":7,"length":6,"solvingMode":0,"selected":false},{"isAcross":true,"id":8,"x":1,"y":9,"length":4,"solvingMode":0,"selected":false},{"isAcross":true,"id":9,"x":6,"y":9,"length":8,"solvingMode":0,"selected":false},{"isAcross":true,"id":10,"x":1,"y":11,"length":9,"solvingMode":0,"selected":false},{"isAcross":true,"id":11,"x":11,"y":11,"length":3,"solvingMode":0,"selected":false},{"isAcross":true,"id":12,"x":2,"y":13,"length":11,"solvingMode":0,"selected":false},{"isAcross":false,"id":13,"x":3,"y":1,"length":5,"solvingMode":0,"selected":false},{"isAcross":false,"id":14,"x":5,"y":1,"length":8,"solvingMode":0,"selected":false},{"isAcross":false,"id":15,"x":7,"y":1,"length":6,"solvingMode":0,"selected":false},{"isAcross":false,"id":16,"x":9,"y":1,"length":4,"solvingMode":0,"selected":false},{"isAcross":false,"id":17,"x":11,"y":1,"length":7,"solvingMode":0,"selected":false},{"isAcross":false,"id":18,"x":1,"y":2,"length":11,"solvingMode":0,"selected":false},{"isAcross":false,"id":19,"x":13,"y":2,"length":11,"solvingMode":0,"selected":false},{"isAcross":false,"id":20,"x":9,"y":6,"length":8,"solvingMode":0,"selected":false},{"isAcross":false,"id":21,"x":3,"y":7,"length":7,"solvingMode":0,"selected":false},{"isAcross":false,"id":22,"x":7,"y":8,"length":6,"solvingMode":0,"selected":false},{"isAcross":false,"id":23,"x":11,"y":9,"length":5,"solvingMode":0,"selected":false},{"isAcross":false,"id":24,"x":5,"y":10,"length":4,"solvingMode":0,"selected":false}]}