{"clueProviders":[{"name":"Cryptic","acrossClues":[{"format":"11","text":"Putting out commercials, devising art, possibly?","number":"1","wordId":1},{"format":"3","text":"And in France get a hundred &ndash; and the rest (abbrev)","number":"9","wordId":2},{"format":"9","text":"Three fear confusion from now on","number":"10","wordId":3},{"format":"8","text":"Start of disease when away on holiday","number":"11","wordId":4},{"format":"4","text":"Thread of a story?","number":"12","wordId":5},{"format":"6","text":"Chief is calling monetary centre","number":"14","wordId":6},{"format":"6","text":"A dunce returned with hot back-scrubber","number":"16","wordId":7},{"format":"4","text":"Journey some take into Urals","number":"18","wordId":8},{"format":"8","text":"Sit on sled and dart off","number":"19","wordId":9},{"format":"9","text":"Wandering Arab's lost bird","number":"22","wordId":10},{"format":"3","text":"Accelerate in hire vehicle","number":"23","wordId":11},{"format":"8,3","text":"Poor Peter cheats but is class favourite","number":"24","wordId":12}],"downClues":[{"format":"5","text":"Old coin put away in pipe","number":"2","wordId":13},{"format":"8","text":"There, there, a large part is heavenly","number":"3","wordId":14},{"format":"6","text":"Temperature of the city seen in Sikh headgear","number":"4","wordId":15},{"format":"4","text":"In-house, a rival brand","number":"5","wordId":16},{"format":"3,4","text":"Rather hot flan coming out","number":"6","wordId":17},{"format":"3,3,5","text":"Aristocrat in Maltese development to vent anger","number":"7","wordId":18},{"format":"6,5","text":"Dawn departure is unauthorised absence","number":"8","wordId":19},{"format":"8","text":"Girl in some trouble that's sticky","number":"13","wordId":20},{"format":"7","text":"Second fall on the trip","number":"15","wordId":21},{"format":"6","text":"Seen in bistro, beautiful flashing light","number":"17","wordId":22},{"format":"5","text":"Lament Reg and I'd composed","number":"20","wordId":23},{"format":"4","text":"Noticing part of the ear","number":"21","wordId":24}]},{"name":"Coffee Time","acrossClues":[{"format":"11","text":"Promoting (products)","number":"1","wordId":1},{"format":"3","text":"And so forth (abbrev)","number":"9","wordId":2},{"format":"9","text":"In future","number":"10","wordId":3},{"format":"8","text":"Flare-up","number":"11","wordId":4},{"format":"4","text":"Anecdote","number":"12","wordId":5},{"format":"6","text":"Budgetary","number":"14","wordId":6},{"format":"6","text":"Back-scrubber","number":"16","wordId":7},{"format":"4","text":"Excursion","number":"18","wordId":8},{"format":"8","text":"Extend across","number":"19","wordId":9},{"format":"9","text":"Huge seabird","number":"22","wordId":10},{"format":"3","text":"Race (an engine)","number":"23","wordId":11},{"format":"8,3","text":"Classroom favourite","number":"24","wordId":12}],"downClues":[{"format":"5","text":"Old Continental coin","number":"2","wordId":13},{"format":"8","text":"Heavenly","number":"3","wordId":14},{"format":"6","text":"Sikh's head-dress","number":"4","wordId":15},{"format":"4","text":"Cauterise","number":"5","wordId":16},{"format":"3,4","text":"I should say!","number":"6","wordId":17},{"format":"3,3,5","text":"Blow your top","number":"7","wordId":18},{"format":"6,5","text":"Unannounced absence","number":"8","wordId":19},{"format":"8","text":"Dark treacle","number":"13","wordId":20},{"format":"7","text":"Fall","number":"15","wordId":21},{"format":"6","text":"Disco light","number":"17","wordId":22},{"format":"5","text":"Dreary song","number":"20","wordId":23},{"format":"4","text":"Of the ear","number":"21","wordId":24}]}],"id":"Sun28203","title":"Sun Crossword No 432009","datePublished":"2017-10-19T00:00:00","dateStarted":null,"duration":0,"solvingMode":0,"grid":[[{"guess":"","letter":"","number":"","selected":false,"wordSelected":false,"solvingMode":0,"autoSolved":false},{"guess":"","letter":"A","number":"1","selected":false,"wordSelected":false,"solvingMode":0,"autoSolved":false},{"guess":"","letter":"D","number":"2","selected":false,"wordSelected":false,"solvingMode":0,"autoSolved":false},{"guess":"","letter":"V","number":"","selected":false,"wordSelected":false,"solvingMode":0,"autoSolved":false},{"guess":"","letter":"E","number":"3","selected":false,"wordSelected":false,"solvingMode":0,"autoSolved":false},{"guess":"","letter":"R","number":"","selected":false,"wordSelected":false,"solvingMode":0,"autoSolved":false},{"guess":"","letter":"T","number":"4","selected":false,"wordSelected":false,"solvingMode":0,"autoSolved":false},{"guess":"","letter":"I","number":"","selected":false,"wordSelected":false,"solvingMode":0,"autoSolved":false},{"guess":"","letter":"S","number":"5","selected":false,"wordSelected":false,"solvingMode":0,"autoSolved":false},{"guess":"","letter":"I","number":"","selected":false,"wordSelected":false,"solvingMode":0,"autoSolved":false},{"guess":"","letter":"N","number":"6","selected":false,"wordSelected":false,"solvingMode":0,"autoSolved":false},{"guess":"","letter":"G","number":"","selected":false,"wordSelected":false,"solvingMode":0,"autoSolved":false},{"guess":"","letter":"","number":"","selected":false,"wordSelected":false,"solvingMode":0,"autoSolved":false}],[{"guess":"","letter":"L","number":"7","selected":false,"wordSelected":false,"solvingMode":0,"autoSolved":false},{"guess":"","letter":"","number":"","selected":false,"wordSelected":false,"solvingMode":0,"autoSolved":false},{"guess":"","letter":"U","number":"","selected":false,"wordSelected":false,"solvingMode":0,"autoSolved":false},{"guess":"","letter":"","number":"","selected":false,"wordSelected":false,"solvingMode":0,"autoSolved":false},{"guess":"","letter":"T","number":"","selected":false,"wordSelected":false,"solvingMode":0,"autoSolved":false},{"guess":"","letter":"","number":"","selected":false,"wordSelected":false,"solvingMode":0,"autoSolved":false},{"guess":"","letter":"U","number":"","selected":false,"wordSelected":false,"solvingMode":0,"autoSolved":false},{"guess":"","letter":"","number":"","selected":false,"wordSelected":false,"solvingMode":0,"autoSolved":false},{"guess":"","letter":"E","number":"","selected":false,"wordSelected":false,"solvingMode":0,"autoSolved":false},{"guess":"","letter":"","number":"","selected":false,"wordSelected":false,"solvingMode":0,"autoSolved":false},{"guess":"","letter":"O","number":"","selected":false,"wordSelected":false,"solvingMode":0,"autoSolved":false},{"guess":"","letter":"","number":"","selected":false,"wordSelected":false,"solvingMode":0,"autoSolved":false},{"guess":"","letter":"F","number":"8","selected":false,"wordSelected":false,"solvingMode":0,"autoSolved":false}],[{"guess":"","letter":"E","number":"9","selected":false,"wordSelected":false,"solvingMode":0,"autoSolved":false},{"guess":"","letter":"T","number":"","selected":false,"wordSelected":false,"solvingMode":0,"autoSolved":false},{"guess":"","letter":"C","number":"","selected":false,"wordSelected":false,"solvingMode":0,"autoSolved":false},{"guess":"","letter":"","number":"","selected":false,"wordSelected":false,"solvingMode":0,"autoSolved":false},{"guess":"","letter":"H","number":"10","selected":false,"wordSelected":false,"solvingMode":0,"autoSolved":false},{"guess":"","letter":"E","number":"","selected":false,"wordSelected":false,"solvingMode":0,"autoSolved":false},{"guess":"","letter":"R","number":"","selected":false,"wordSelected":false,"solvingMode":0,"autoSolved":false},{"guess":"","letter":"E","number":"","selected":false,"wordSelected":false,"solvingMode":0,"autoSolved":false},{"guess":"","letter":"A","number":"","selected":false,"wordSelected":false,"solvingMode":0,"autoSolved":false},{"guess":"","letter":"F","number":"","selected":false,"wordSelected":false,"solvingMode":0,"autoSolved":false},{"guess":"","letter":"T","number":"","selected":false,"wordSelected":false,"solvingMode":0,"autoSolved":false},{"guess":"","letter":"E","number":"","selected":false,"wordSelected":false,"solvingMode":0,"autoSolved":false},{"guess":"","letter":"R","number":"","selected":false,"wordSelected":false,"solvingMode":0,"autoSolved":false}],[{"guess":"","letter":"T","number":"","selected":false,"wordSelected":false,"solvingMode":0,"autoSolved":false},{"guess":"","letter":"","number":"","selected":false,"wordSelected":false,"solvingMode":0,"autoSolved":false},{"guess":"","letter":"A","number":"","selected":false,"wordSelected":false,"solvingMode":0,"autoSolved":false},{"guess":"","letter":"","number":"","selected":false,"wordSelected":false,"solvingMode":0,"autoSolved":false},{"guess":"","letter":"E","number":"","selected":false,"wordSelected":false,"solvingMode":0,"autoSolved":false},{"guess":"","letter":"","number":"","selected":false,"wordSelected":false,"solvingMode":0,"autoSolved":false},{"guess":"","letter":"B","number":"","selected":false,"wordSelected":false,"solvingMode":0,"autoSolved":false},{"guess":"","letter":"","number":"","selected":false,"wordSelected":false,"solvingMode":0,"autoSolved":false},{"guess":"","letter":"R","number":"","selected":false,"wordSelected":false,"solvingMode":0,"autoSolved":false},{"guess":"","letter":"","number":"","selected":false,"wordSelected":false,"solvingMode":0,"autoSolved":false},{"guess":"","letter":"H","number":"","selected":false,"wordSelected":false,"solvingMode":0,"autoSolved":false},{"guess":"","letter":"","number":"","selected":false,"wordSelected":false,"solvingMode":0,"autoSolved":false},{"guess":"","letter":"E","number":"","selected":false,"wordSelected":false,"solvingMode":0,"autoSolved":false}],[{"guess":"","letter":"O","number":"11","selected":false,"wordSelected":false,"solvingMode":0,"autoSolved":false},{"guess":"","letter":"U","number":"","selected":false,"wordSelected":false,"solvingMode":0,"autoSolved":false},{"guess":"","letter":"T","number":"","selected":false,"wordSelected":false,"solvingMode":0,"autoSolved":false},{"guess":"","letter":"B","number":"","selected":false,"wordSelected":false,"solvingMode":0,"autoSolved":false},{"guess":"","letter":"R","number":"","selected":false,"wordSelected":false,"solvingMode":0,"autoSolved":false},{"guess":"","letter":"E","number":"","selected":false,"wordSelected":false,"solvingMode":0,"autoSolved":false},{"guess":"","letter":"A","number":"","selected":false,"wordSelected":false,"solvingMode":0,"autoSolved":false},{"guess":"","letter":"K","number":"","selected":false,"wordSelected":false,"solvingMode":0,"autoSolved":false},{"guess":"","letter":"","number":"","selected":false,"wordSelected":false,"solvingMode":0,"autoSolved":false},{"guess":"","letter":"Y","number":"12","selected":false,"wordSelected":false,"solvingMode":0,"autoSolved":false},{"guess":"","letter":"A","number":"","selected":false,"wordSelected":false,"solvingMode":0,"autoSolved":false},{"guess":"","letter":"R","number":"","selected":false,"wordSelected":false,"solvingMode":0,"autoSolved":false},{"guess":"","letter":"N","number":"","selected":false,"wordSelected":false,"solvingMode":0,"autoSolved":false}],[{"guess":"","letter":"F","number":"","selected":false,"wordSelected":false,"solvingMode":0,"autoSolved":false},{"guess":"","letter":"","number":"","selected":false,"wordSelected":false,"solvingMode":0,"autoSolved":false},{"guess":"","letter":"","number":"","selected":false,"wordSelected":false,"solvingMode":0,"autoSolved":false},{"guess":"","letter":"","number":"","selected":false,"wordSelected":false,"solvingMode":0,"autoSolved":false},{"guess":"","letter":"E","number":"","selected":false,"wordSelected":false,"solvingMode":0,"autoSolved":false},{"guess":"","letter":"","number":"","selected":false,"wordSelected":false,"solvingMode":0,"autoSolved":false},{"guess":"","letter":"N","number":"","selected":false,"wordSelected":false,"solvingMode":0,"autoSolved":false},{"guess":"","letter":"","number":"","selected":false,"wordSelected":false,"solvingMode":0,"autoSolved":false},{"guess":"","letter":"M","number":"13","selected":false,"wordSelected":false,"solvingMode":0,"autoSolved":false},{"guess":"","letter":"","number":"","selected":false,"wordSelected":false,"solvingMode":0,"autoSolved":false},{"guess":"","letter":"L","number":"","selected":false,"wordSelected":false,"solvingMode":0,"autoSolved":false},{"guess":"","letter":"","number":"","selected":false,"wordSelected":false,"solvingMode":0,"autoSolved":false},{"guess":"","letter":"C","number":"","selected":false,"wordSelected":false,"solvingMode":0,"autoSolved":false}],[{"guess":"","letter":"F","number":"14","selected":false,"wordSelected":false,"solvingMode":0,"autoSolved":false},{"guess":"","letter":"I","number":"","selected":false,"wordSelected":false,"solvingMode":0,"autoSolved":false},{"guess":"","letter":"S","number":"15","selected":false,"wordSelected":false,"solvingMode":0,"autoSolved":false},{"guess":"","letter":"C","number":"","selected":false,"wordSelected":false,"solvingMode":0,"autoSolved":false},{"guess":"","letter":"A","number":"","selected":false,"wordSelected":false,"solvingMode":0,"autoSolved":false},{"guess":"","letter":"L","number":"","selected":false,"wordSelected":false,"solvingMode":0,"autoSolved":false},{"guess":"","letter":"","number":"","selected":false,"wordSelected":false,"solvingMode":0,"autoSolved":false},{"guess":"","letter":"L","number":"16","selected":false,"wordSelected":false,"solvingMode":0,"autoSolved":false},{"guess":"","letter":"O","number":"","selected":false,"wordSelected":false,"solvingMode":0,"autoSolved":false},{"guess":"","letter":"O","number":"","selected":false,"wordSelected":false,"solvingMode":0,"autoSolved":false},{"guess":"","letter":"F","number":"","selected":false,"wordSelected":false,"solvingMode":0,"autoSolved":false},{"guess":"","letter":"A","number":"","selected":false,"wordSelected":false,"solvingMode":0,"autoSolved":false},{"guess":"","letter":"H","number":"","selected":false,"wordSelected":false,"solvingMode":0,"autoSolved":false}],[{"guess":"","letter":"S","number":"","selected":false,"wordSelected":false,"solvingMode":0,"autoSolved":false},{"guess":"","letter":"","number":"","selected":false,"wordSelected":false,"solvingMode":0,"autoSolved":false},{"guess":"","letter":"T","number":"","selected":false,"wordSelected":false,"solvingMode":0,"autoSolved":false},{"guess":"","letter":"","number":"","selected":false,"wordSelected":false,"solvingMode":0,"autoSolved":false},{"guess":"","letter":"L","number":"","selected":false,"wordSelected":false,"solvingMode":0,"autoSolved":false},{"guess":"","letter":"","number":"","selected":false,"wordSelected":false,"solvingMode":0,"autoSolved":false},{"guess":"","letter":"S","number":"17","selected":false,"wordSelected":false,"solvingMode":0,"autoSolved":false},{"guess":"","letter":"","number":"","selected":false,"wordSelected":false,"solvingMode":0,"autoSolved":false},{"guess":"","letter":"L","number":"","selected":false,"wordSelected":false,"solvingMode":0,"autoSolved":false},{"guess":"","letter":"","number":"","selected":false,"wordSelected":false,"solvingMode":0,"autoSolved":false},{"guess":"","letter":"","number":"","selected":false,"wordSelected":false,"solvingMode":0,"autoSolved":false},{"guess":"","letter":"","number":"","selected":false,"wordSelected":false,"solvingMode":0,"autoSolved":false},{"guess":"","letter":"L","number":"","selected":false,"wordSelected":false,"solvingMode":0,"autoSolved":false}],[{"guess":"","letter":"T","number":"18","selected":false,"wordSelected":false,"solvingMode":0,"autoSolved":false},{"guess":"","letter":"O","number":"","selected":false,"wordSelected":false,"solvingMode":0,"autoSolved":false},{"guess":"","letter":"U","number":"","selected":false,"wordSelected":false,"solvingMode":0,"autoSolved":false},{"guess":"","letter":"R","number":"","selected":false,"wordSelected":false,"solvingMode":0,"autoSolved":false},{"guess":"","letter":"","number":"","selected":false,"wordSelected":false,"solvingMode":0,"autoSolved":false},{"guess":"","letter":"S","number":"19","selected":false,"wordSelected":false,"solvingMode":0,"autoSolved":false},{"guess":"","letter":"T","number":"","selected":false,"wordSelected":false,"solvingMode":0,"autoSolved":false},{"guess":"","letter":"R","number":"","selected":false,"wordSelected":false,"solvingMode":0,"autoSolved":false},{"guess":"","letter":"A","number":"","selected":false,"wordSelected":false,"solvingMode":0,"autoSolved":false},{"guess":"","letter":"D","number":"","selected":false,"wordSelected":false,"solvingMode":0,"autoSolved":false},{"guess":"","letter":"D","number":"20","selected":false,"wordSelected":false,"solvingMode":0,"autoSolved":false},{"guess":"","letter":"L","number":"","selected":false,"wordSelected":false,"solvingMode":0,"autoSolved":false},{"guess":"","letter":"E","number":"","selected":false,"wordSelected":false,"solvingMode":0,"autoSolved":false}],[{"guess":"","letter":"E","number":"","selected":false,"wordSelected":false,"solvingMode":0,"autoSolved":false},{"guess":"","letter":"","number":"","selected":false,"wordSelected":false,"solvingMode":0,"autoSolved":false},{"guess":"","letter":"M","number":"","selected":false,"wordSelected":false,"solvingMode":0,"autoSolved":false},{"guess":"","letter":"","number":"","selected":false,"wordSelected":false,"solvingMode":0,"autoSolved":false},{"guess":"","letter":"O","number":"21","selected":false,"wordSelected":false,"solvingMode":0,"autoSolved":false},{"guess":"","letter":"","number":"","selected":false,"wordSelected":false,"solvingMode":0,"autoSolved":false},{"guess":"","letter":"R","number":"","selected":false,"wordSelected":false,"solvingMode":0,"autoSolved":false},{"guess":"","letter":"","number":"","selected":false,"wordSelected":false,"solvingMode":0,"autoSolved":false},{"guess":"","letter":"S","number":"","selected":false,"wordSelected":false,"solvingMode":0,"autoSolved":false},{"guess":"","letter":"","number":"","selected":false,"wordSelected":false,"solvingMode":0,"autoSolved":false},{"guess":"","letter":"I","number":"","selected":false,"wordSelected":false,"solvingMode":0,"autoSolved":false},{"guess":"","letter":"","number":"","selected":false,"wordSelected":false,"solvingMode":0,"autoSolved":false},{"guess":"","letter":"A","number":"","selected":false,"wordSelected":false,"solvingMode":0,"autoSolved":false}],[{"guess":"","letter":"A","number":"22","selected":false,"wordSelected":false,"solvingMode":0,"autoSolved":false},{"guess":"","letter":"L","number":"","selected":false,"wordSelected":false,"solvingMode":0,"autoSolved":false},{"guess":"","letter":"B","number":"","selected":false,"wordSelected":false,"solvingMode":0,"autoSolved":false},{"guess":"","letter":"A","number":"","selected":false,"wordSelected":false,"solvingMode":0,"autoSolved":false},{"guess":"","letter":"T","number":"","selected":false,"wordSelected":false,"solvingMode":0,"autoSolved":false},{"guess":"","letter":"R","number":"","selected":false,"wordSelected":false,"solvingMode":0,"autoSolved":false},{"guess":"","letter":"O","number":"","selected":false,"wordSelected":false,"solvingMode":0,"autoSolved":false},{"guess":"","letter":"S","number":"","selected":false,"wordSelected":false,"solvingMode":0,"autoSolved":false},{"guess":"","letter":"S","number":"","selected":false,"wordSelected":false,"solvingMode":0,"autoSolved":false},{"guess":"","letter":"","number":"","selected":false,"wordSelected":false,"solvingMode":0,"autoSolved":false},{"guess":"","letter":"R","number":"23","selected":false,"wordSelected":false,"solvingMode":0,"autoSolved":false},{"guess":"","letter":"E","number":"","selected":false,"wordSelected":false,"solvingMode":0,"autoSolved":false},{"guess":"","letter":"V","number":"","selected":false,"wordSelected":false,"solvingMode":0,"autoSolved":false}],[{"guess":"","letter":"M","number":"","selected":false,"wordSelected":false,"solvingMode":0,"autoSolved":false},{"guess":"","letter":"","number":"","selected":false,"wordSelected":false,"solvingMode":0,"autoSolved":false},{"guess":"","letter":"L","number":"","selected":false,"wordSelected":false,"solvingMode":0,"autoSolved":false},{"guess":"","letter":"","number":"","selected":false,"wordSelected":false,"solvingMode":0,"autoSolved":false},{"guess":"","letter":"I","number":"","selected":false,"wordSelected":false,"solvingMode":0,"autoSolved":false},{"guess":"","letter":"","number":"","selected":false,"wordSelected":false,"solvingMode":0,"autoSolved":false},{"guess":"","letter":"B","number":"","selected":false,"wordSelected":false,"solvingMode":0,"autoSolved":false},{"guess":"","letter":"","number":"","selected":false,"wordSelected":false,"solvingMode":0,"autoSolved":false},{"guess":"","letter":"E","number":"","selected":false,"wordSelected":false,"solvingMode":0,"autoSolved":false},{"guess":"","letter":"","number":"","selected":false,"wordSelected":false,"solvingMode":0,"autoSolved":false},{"guess":"","letter":"G","number":"","selected":false,"wordSelected":false,"solvingMode":0,"autoSolved":false},{"guess":"","letter":"","number":"","selected":false,"wordSelected":false,"solvingMode":0,"autoSolved":false},{"guess":"","letter":"E","number":"","selected":false,"wordSelected":false,"solvingMode":0,"autoSolved":false}],[{"guess":"","letter":"","number":"","selected":false,"wordSelected":false,"solvingMode":0,"autoSolved":false},{"guess":"","letter":"T","number":"24","selected":false,"wordSelected":false,"solvingMode":0,"autoSolved":false},{"guess":"","letter":"E","number":"","selected":false,"wordSelected":false,"solvingMode":0,"autoSolved":false},{"guess":"","letter":"A","number":"","selected":false,"wordSelected":false,"solvingMode":0,"autoSolved":false},{"guess":"","letter":"C","number":"","selected":false,"wordSelected":false,"solvingMode":0,"autoSolved":false},{"guess":"","letter":"H","number":"","selected":false,"wordSelected":false,"solvingMode":0,"autoSolved":false},{"guess":"","letter":"E","number":"","selected":false,"wordSelected":false,"solvingMode":0,"autoSolved":false},{"guess":"","letter":"R","number":"","selected":false,"wordSelected":false,"solvingMode":0,"autoSolved":false},{"guess":"","letter":"S","number":"","selected":false,"wordSelected":false,"solvingMode":0,"autoSolved":false},{"guess":"","letter":"P","number":"","selected":false,"wordSelected":false,"solvingMode":0,"autoSolved":false},{"guess":"","letter":"E","number":"","selected":false,"wordSelected":false,"solvingMode":0,"autoSolved":false},{"guess":"","letter":"T","number":"","selected":false,"wordSelected":false,"solvingMode":0,"autoSolved":false},{"guess":"","letter":"","number":"","selected":false,"wordSelected":false,"solvingMode":0,"autoSolved":false}]],"words":[{"isAcross":true,"id":1,"x":2,"y":1,"length":11,"solvingMode":0,"selected":false},{"isAcross":true,"id":2,"x":1,"y":3,"length":3,"solvingMode":0,"selected":false},{"isAcross":true,"id":3,"x":5,"y":3,"length":9,"solvingMode":0,"selected":false},{"isAcross":true,"id":4,"x":1,"y":5,"length":8,"solvingMode":0,"selected":false},{"isAcross":true,"id":5,"x":10,"y":5,"length":4,"solvingMode":0,"selected":false},{"isAcross":true,"id":6,"x":1,"y":7,"length":6,"solvingMode":0,"selected":false},{"isAcross":true,"id":7,"x":8,"y":7,"length":6,"solvingMode":0,"selected":false},{"isAcross":true,"id":8,"x":1,"y":9,"length":4,"solvingMode":0,"selected":false},{"isAcross":true,"id":9,"x":6,"y":9,"length":8,"solvingMode":0,"selected":false},{"isAcross":true,"id":10,"x":1,"y":11,"length":9,"solvingMode":0,"selected":false},{"isAcross":true,"id":11,"x":11,"y":11,"length":3,"solvingMode":0,"selected":false},{"isAcross":true,"id":12,"x":2,"y":13,"length":11,"solvingMode":0,"selected":false},{"isAcross":false,"id":13,"x":3,"y":1,"length":5,"solvingMode":0,"selected":false},{"isAcross":false,"id":14,"x":5,"y":1,"length":8,"solvingMode":0,"selected":false},{"isAcross":false,"id":15,"x":7,"y":1,"length":6,"solvingMode":0,"selected":false},{"isAcross":false,"id":16,"x":9,"y":1,"length":4,"solvingMode":0,"selected":false},{"isAcross":false,"id":17,"x":11,"y":1,"length":7,"solvingMode":0,"selected":false},{"isAcross":false,"id":18,"x":1,"y":2,"length":11,"solvingMode":0,"selected":false},{"isAcross":false,"id":19,"x":13,"y":2,"length":11,"solvingMode":0,"selected":false},{"isAcross":false,"id":20,"x":9,"y":6,"length":8,"solvingMode":0,"selected":false},{"isAcross":false,"id":21,"x":3,"y":7,"length":7,"solvingMode":0,"selected":false},{"isAcross":false,"id":22,"x":7,"y":8,"length":6,"solvingMode":0,"selected":false},{"isAcross":false,"id":23,"x":11,"y":9,"length":5,"solvingMode":0,"selected":false},{"isAcross":false,"id":24,"x":5,"y":10,"length":4,"solvingMode":0,"selected":false}]}